[
    {
        "id": "2492f43b-80f1-4469-8c9f-2ab3c821ee81",
        "name": "Vedant Choudhari",
        "username": "vc12",
        "password": "$2b$12$bWpBxLXuOZ1mvwPV8LlIguos/NtfFmxrixvjk/YLiyAe3tUgsxESO",
        "security_question": "What city were you born in?",
        "security_answer": "hh",
        "created_at": "2025-09-18T12:41:37.333628"
    },
    {
        "id": "6af40dd6-e45f-4d28-904b-eb6e28c890ed",
        "name": "vvv",
        "username": "vv111",
        "password": "$2b$12$.bys8J7oDWAJ02GsXrPSPucTst.QWS2NJw7W1DRc7TwrbAqf0d7l.",
        "security_question": "What city were you born in?",
        "security_answer": "www",
        "created_at": "2025-09-18T17:59:17.074308"
    },
    {
        "id": "982abbe2-9b81-48e0-9976-9ad9d448bb6e",
        "name": "vc",
        "username": "vc",
        "password": "$2b$12$49gBtPBTQB8pNO1Rh/REo.kV.ZUAjMztSiI5AHdcJsEjvhvYmn.oK",
        "security_question": "What city were you born in?",
        "security_answer": "vc",
        "created_at": "2025-09-18T17:59:50.820909"
    },
    {
        "id": "7a48a1b4-e218-4128-8787-17bc80edaffc",
        "name": "Verification User",
        "username": "verifier_user",
        "password": "$2b$12$JeAOAuIpG9u8ahWB.356Le3YYzqC7fHOvQ96BaB/5EkHmfIufl1Aa",
        "security_question": "What city were you born in?",
        "security_answer": "$2b$12$NW37uGFxGcwklhsxDuedHuC8hEE4P/kTyRhVPppiGgfQyXjOuRFOW",
        "created_at": "2026-07-15T18:46:47.553092"
    },
    {
        "id": "3ef5b573-64f2-4c88-aba5-25abf4991f1e",
        "name": "vedant",
        "username": "vedant",
        "password": "$2b$12$18zNDqZ5zRay6CcOARKUPelgTp4YucqSUC6Y8Zq6CCuJuhKA46h4e",
        "security_question": "What was your first school?",
        "security_answer": "$2b$12$ivbDAprXN391SE4BpEJcmublVNhp1/gNnZAm3LE7ha5ZYfsKXNvz2",
        "created_at": "2026-07-15T18:52:42.271715"
    }
]